kupo/__init__.py
kupo/client.py
kupo/models.py
kupo/utils.py
kupo_py-0.1.2.dist-info/METADATA
kupo_py-0.1.2.dist-info/WHEEL
kupo_py-0.1.2.dist-info/licenses/LICENSE
kupo_py-0.1.2.dist-info/RECORD
